privue/__init__.py
privue/client/__init__.py
privue/client/client.py
privue/errors/__init__.py
privue/errors/errors.py
privue/server/__init__.py
privue/server/server.py
privue/util/__init__.py
privue/util/util.py
privue-0.12.dist-info/METADATA
privue-0.12.dist-info/WHEEL
privue-0.12.dist-info/top_level.txt
privue-0.12.dist-info/RECORD
