Metadata-Version: 2.1
Name: privue
Version: 0.12
Requires-Dist: numpy
Requires-Dist: pandas
